{
    "version": "2.1.604",
    "architecture": {
        "32bit": {
            "url": "https://github.com/lawrencegripper/azbrowse/releases/download/v2.1.604/azbrowse_windows_386.zip",
            "bin": [
                "azbrowse.exe"
            ],
            "hash": "8015142d100b949018361045378025c53a6853cfc3ab74172643d20432763977"
        },
        "64bit": {
            "url": "https://github.com/lawrencegripper/azbrowse/releases/download/v2.1.604/azbrowse_windows_amd64.zip",
            "bin": [
                "azbrowse.exe"
            ],
            "hash": "db29d719aa83d9892fb507499c9d347ed5b6e34dc03bb17692df97151ef87fdb"
        }
    },
    "homepage": "https://github.com/lawrencegripper/azbrowse",
    "license": "MIT",
    "description": "An interactive CLI for browsing Azure, inspired by http://resources.azure.com/"
}