{
    "version": "1.1.505",
    "architecture": {
        "32bit": {
            "url": "https://github.com/lawrencegripper/azbrowse/releases/download/v1.1.505/azbrowse_windows_386.zip",
            "bin": [
                "azbrowse.exe"
            ],
            "hash": "9d58922fe44239a5e68ff7fb3d0475309a703fbcfa2e0cbba71ecdbf6d8c784a"
        },
        "64bit": {
            "url": "https://github.com/lawrencegripper/azbrowse/releases/download/v1.1.505/azbrowse_windows_amd64.zip",
            "bin": [
                "azbrowse.exe"
            ],
            "hash": "a7a70d1e4e76da64be662278c12b57ae5a3e5c71420751477d67803cc96fda21"
        }
    },
    "homepage": "https://github.com/lawrencegripper/azbrowse",
    "license": "MIT",
    "description": "An interactive CLI for browsing Azure, inspired by http://resources.azure.com/"
}