{
    "version": "1.1.429",
    "architecture": {
        "32bit": {
            "url": "https://github.com/lawrencegripper/azbrowse/releases/download/v1.1.429/azbrowse_windows_386.zip",
            "bin": [
                "azbrowse.exe"
            ],
            "hash": "48abcddf71e8c649a43f8c6af6e58d839249cc2731df1c4de9e55415d74d87b1"
        },
        "64bit": {
            "url": "https://github.com/lawrencegripper/azbrowse/releases/download/v1.1.429/azbrowse_windows_amd64.zip",
            "bin": [
                "azbrowse.exe"
            ],
            "hash": "a8c292e6875760a493ffae69088e756f96b6e1ecc1ba6503202d0314d72cebc9"
        }
    },
    "homepage": "https://github.com/lawrencegripper/azbrowse",
    "license": "MIT",
    "description": "An interactive CLI for browsing Azure, inspired by http://resources.azure.com/"
}